LICENSE
MANIFEST.in
README.md
setup.py
lcp.libpythonpro.egg-info/PKG-INFO
lcp.libpythonpro.egg-info/SOURCES.txt
lcp.libpythonpro.egg-info/dependency_links.txt
lcp.libpythonpro.egg-info/not-zip-safe
lcp.libpythonpro.egg-info/requires.txt
lcp.libpythonpro.egg-info/top_level.txt
libpythonpro/__init__.py
libpythonpro/github_api.py