Metadata-Version: 2.1
Name: lcp.libpythonpro
Version: 0.2
Summary: Módulo para exemplificar construção de projetos Python no curso Pytools
Home-page: https://github.com/ludmilacp/libpythonpro
Author: Ludmila Canfield Pereira
Author-email: ludmila@gmail.com
License: GNU Affero General Public License v3 or latters (AGPL v3+)
Platform: UNKNOWN
Classifier: Development Status :: 2 - Pre-Alpha
Classifier: Environment :: Console
Classifier: Intended Audience :: Developers
Classifier: License :: OSI Approved :: GNU Affero General Public License v3 or later (AGPLv3+)
Classifier: Operating System :: OS Independent
Classifier: Programming Language :: Python :: 3.8
Classifier: Framework :: Pytest
